llama/__init__.py
llama/engine/constants.py
llama/engine/score_selector.py
llama/error/error.py
llama/metrics/compare_equal_metric.py
llama/metrics/metric.py
llama/program/builder.py
llama/program/function.py
llama/program/program.py
llama/program/value.py
llama/program/operations/batch_llama_operation.py
llama/program/operations/call_operation.py
llama/program/operations/feedback_operation.py
llama/program/operations/get_argument_operation.py
llama/program/operations/get_element_operation.py
llama/program/operations/get_field_operation.py
llama/program/operations/llama_operation.py
llama/program/operations/metric_operation.py
llama/program/operations/return_operation.py
llama/program/util/config.py
llama/program/util/run_ai.py
llama/program/util/type_to_dict.py
llama/types/base_specification.py
llama/types/context.py
llama/types/type.py
llamada-0.0.1.dist-info/LICENSE
llamada-0.0.1.dist-info/METADATA
llamada-0.0.1.dist-info/WHEEL
llamada-0.0.1.dist-info/top_level.txt
llamada-0.0.1.dist-info/RECORD
